LICENSE
README.md
setup.cfg
setup.py
jcopvision/__init__.py
jcopvision/exception.py
jcopvision/model_selection.py
jcopvision/yolo.py
jcopvision.egg-info/PKG-INFO
jcopvision.egg-info/SOURCES.txt
jcopvision.egg-info/dependency_links.txt
jcopvision.egg-info/requires.txt
jcopvision.egg-info/top_level.txt
jcopvision/draw/__init__.py
jcopvision/draw/bbox.py
jcopvision/draw/circle.py
jcopvision/draw/imshow.py
jcopvision/draw/line.py
jcopvision/draw/text.py
jcopvision/image_processing/__init__.py
jcopvision/image_processing/blending.py
jcopvision/image_processing/enhancement.py
jcopvision/image_processing/masking.py
jcopvision/io/__init__.py
jcopvision/io/dataset.py
jcopvision/io/jupyter.py
jcopvision/io/reader.py
jcopvision/io/utils.py
jcopvision/io/writer.py
jcopvision/utils/__init__.py
jcopvision/utils/background.py
jcopvision/utils/bbox.py
jcopvision/utils/color.py
jcopvision/utils/filter.py
jcopvision/utils/image.py
jcopvision/utils/landmark.py